{"users":[{"id":43927,"username":"aqusvs","name":"Gustav G.","avatar_template":"/letter_avatar_proxy/v4/letter/a/bb73d2/{size}.png"},{"id":43853,"username":"nordik","name":"Leon Wöste","avatar_template":"/user_avatar/leakfree.org/nordik/{size}/5966_2.png"},{"id":43618,"username":"Sarsath","name":"Sarsath","avatar_template":"/letter_avatar_proxy/v4/letter/s/8491ac/{size}.png"},{"id":299,"username":"CatzEyes93","name":"Catzeyes93","avatar_template":"/user_avatar/leakfree.org/catzeyes93/{size}/4402_2.png"},{"id":5060,"username":"CPU","name":"","avatar_template":"/user_avatar/leakfree.org/cpu/{size}/4349_2.png"},{"id":40754,"username":"RedEye","name":"blue","avatar_template":"/user_avatar/leakfree.org/redeye/{size}/4899_2.png"},{"id":44022,"username":"lucaswilde","name":"Lucas Wilde","avatar_template":"/user_avatar/leakfree.org/lucaswilde/{size}/6121_2.png"},{"id":44029,"username":"Thompson","name":"","avatar_template":"/letter_avatar_proxy/v4/letter/t/d6d6ee/{size}.png"},{"id":44019,"username":"raould","name":"raoul duke","avatar_template":"/letter_avatar_proxy/v4/letter/r/8baadc/{size}.png"},{"id":43793,"username":"Fr1m0900","name":"Fr1m","avatar_template":"/letter_avatar_proxy/v4/letter/f/f6c823/{size}.png"},{"id":43017,"username":"Tuc0","name":"","avatar_template":"/letter_avatar_proxy/v4/letter/t/8edcca/{size}.png"},{"id":6789,"username":"Medkit","name":"Bbenjoe","avatar_template":"/letter_avatar_proxy/v4/letter/m/57b2e6/{size}.png"},{"id":351,"username":"Cpl.1nsane","name":"Johnathan Welsh","avatar_template":"/user_avatar/leakfree.org/cpl.1nsane/{size}/4631_2.png"},{"id":39919,"username":"mr.StevenS","name":"Putnikst","avatar_template":"/letter_avatar_proxy/v4/letter/m/ba9def/{size}.png"},{"id":518,"username":"Threeplee","name":"","avatar_template":"/letter_avatar_proxy/v4/letter/t/49beb7/{size}.png"},{"id":43003,"username":"CroakerFrog","name":"Sethcollinson","avatar_template":"/letter_avatar_proxy/v4/letter/c/a4c791/{size}.png"},{"id":43721,"username":"Milloni","name":"Eren","avatar_template":"/letter_avatar_proxy/v4/letter/m/c6cbf5/{size}.png"},{"id":40529,"username":"RedEye9","name":"RedEye9","avatar_template":"/user_avatar/leakfree.org/redeye9/{size}/4342_2.png"},{"id":22194,"username":"Flavrans","name":"Flavrans","avatar_template":"/user_avatar/leakfree.org/flavrans/{size}/4375_2.png"},{"id":44006,"username":"Nazxul360","name":"","avatar_template":"/letter_avatar_proxy/v4/letter/n/bb73d2/{size}.png"},{"id":44005,"username":"dino","name":"","avatar_template":"/letter_avatar_proxy/v4/letter/d/e95f7d/{size}.png"},{"id":43921,"username":"Dallan","name":"Dallan","avatar_template":"/letter_avatar_proxy/v4/letter/d/4bbf92/{size}.png"},{"id":44003,"username":"NumesSanguis","name":"","avatar_template":"/letter_avatar_proxy/v4/letter/n/74df32/{size}.png"},{"id":43946,"username":"Catsmack","name":"Richard Rodgers","avatar_template":"/user_avatar/leakfree.org/catsmack/{size}/6058_2.png"},{"id":43733,"username":"caio2211","name":"Caio","avatar_template":"/letter_avatar_proxy/v4/letter/c/fbc32d/{size}.png"},{"id":43805,"username":"Remnant214","name":"John Lee","avatar_template":"/letter_avatar_proxy/v4/letter/r/da6949/{size}.png"},{"id":43955,"username":"killemall","name":"Thomas M White","avatar_template":"/letter_avatar_proxy/v4/letter/k/9d8465/{size}.png"},{"id":43916,"username":"jmorrismv","name":"Jonathan N Morris","avatar_template":"/letter_avatar_proxy/v4/letter/j/f14d63/{size}.png"},{"id":44001,"username":"NigelHellhound","name":"Israel Brooks","avatar_template":"/user_avatar/leakfree.org/nigelhellhound/{size}/6106_2.png"},{"id":43991,"username":"sam.devray","name":"","avatar_template":"/letter_avatar_proxy/v4/letter/s/a88e4f/{size}.png"},{"id":44000,"username":"pot8o","name":null,"avatar_template":"/letter_avatar_proxy/v4/letter/p/f14d63/{size}.png"},{"id":43963,"username":"LimeSquidBlackMesa","name":"","avatar_template":"/letter_avatar_proxy/v4/letter/l/8edcca/{size}.png"},{"id":39769,"username":"Crawfish","name":"Crawmak","avatar_template":"/user_avatar/leakfree.org/crawfish/{size}/4372_2.png"},{"id":43901,"username":"danbaker","name":"Daniel ","avatar_template":"/letter_avatar_proxy/v4/letter/d/7c8e57/{size}.png"},{"id":2643,"username":"Conti","name":"Conti","avatar_template":"/letter_avatar_proxy/v4/letter/c/c67d28/{size}.png"},{"id":18192,"username":"jakeerc","name":"Jaka","avatar_template":"/letter_avatar_proxy/v4/letter/j/96bed5/{size}.png"},{"id":1014,"username":"dky.tehkingd.u","name":"","avatar_template":"/user_avatar/leakfree.org/dky.tehkingd.u/{size}/4377_2.png"},{"id":14297,"username":"RossBondReturns","name":"Rossbond","avatar_template":"/letter_avatar_proxy/v4/letter/r/838e76/{size}.png"},{"id":43999,"username":"Andyv","name":"","avatar_template":"/letter_avatar_proxy/v4/letter/a/9fc29f/{size}.png"},{"id":43995,"username":"BrabavanDubatan","name":"","avatar_template":"/letter_avatar_proxy/v4/letter/b/5e9695/{size}.png"},{"id":4458,"username":"OrderOfDagon","name":"Flyingpolyp","avatar_template":"/user_avatar/leakfree.org/orderofdagon/{size}/4963_2.png"},{"id":40409,"username":"Admiral_Sakai","name":"Admiral Sakai","avatar_template":"/user_avatar/leakfree.org/admiral_sakai/{size}/4388_2.png"},{"id":43327,"username":"PotatoMuffin","name":"Reagansherwood","avatar_template":"/user_avatar/leakfree.org/potatomuffin/{size}/4509_2.png"},{"id":1068,"username":"darkone","name":"Warbrand2","avatar_template":"/user_avatar/leakfree.org/darkone/{size}/4296_2.png"},{"id":43992,"username":"hompen","name":"","avatar_template":"/letter_avatar_proxy/v4/letter/h/48db29/{size}.png"},{"id":43978,"username":"Vasi","name":"Yusuf GÖL","avatar_template":"/user_avatar/leakfree.org/vasi/{size}/6075_2.png"},{"id":43817,"username":"lord.white","name":"","avatar_template":"/letter_avatar_proxy/v4/letter/l/d26b3c/{size}.png"},{"id":43881,"username":"Snake","name":"Snake","avatar_template":"/letter_avatar_proxy/v4/letter/s/50afbb/{size}.png"},{"id":43911,"username":"Canapin","name":"Coin-coin le Canapin","avatar_template":"/user_avatar/leakfree.org/canapin/{size}/6028_2.png"},{"id":19806,"username":"andrewxc","name":"Andrewxc","avatar_template":"/user_avatar/leakfree.org/andrewxc/{size}/5995_2.png"},{"id":43879,"username":"helpybear","name":"","avatar_template":"/letter_avatar_proxy/v4/letter/h/4bbf92/{size}.png"},{"id":43895,"username":"forgeron","name":"","avatar_template":"/letter_avatar_proxy/v4/letter/f/d9b06d/{size}.png"},{"id":43985,"username":"RaverDave2k","name":"Dave","avatar_template":"/letter_avatar_proxy/v4/letter/r/dbc845/{size}.png"},{"id":43979,"username":"Lilchubby","name":"Adrien","avatar_template":"/letter_avatar_proxy/v4/letter/l/d07c76/{size}.png"},{"id":43940,"username":"grintch","name":"","avatar_template":"/letter_avatar_proxy/v4/letter/g/dc4da7/{size}.png"},{"id":990,"username":"Viewer","name":"Jfjduran","avatar_template":"/letter_avatar_proxy/v4/letter/v/ee7513/{size}.png"},{"id":43975,"username":"Giodude","name":"Giovanni Guarino","avatar_template":"/user_avatar/leakfree.org/giodude/{size}/6074_2.png"},{"id":43971,"username":"neon5916","name":"Rustam Hantimerov","avatar_template":"/letter_avatar_proxy/v4/letter/n/90ced4/{size}.png"}],"primary_groups":[],"topic_list":{"can_create_topic":false,"more_topics_url":"/c/black-mesa-archive/6?page=1","draft":null,"draft_key":"new_topic","draft_sequence":null,"per_page":30,"topics":[{"id":63165,"title":"How did Black Mesa react to the BYDTWD incident at Aperture Science?","fancy_title":"How did Black Mesa react to the BYDTWD incident at Aperture Science?","slug":"how-did-black-mesa-react-to-the-bydtwd-incident-at-aperture-science","posts_count":1,"reply_count":0,"highest_post_number":1,"image_url":null,"created_at":"2020-04-12T15:34:09.015Z","last_posted_at":"2020-04-12T15:34:09.108Z","bumped":true,"bumped_at":"2020-08-12T06:58:02.736Z","archetype":"regular","unseen":false,"pinned":false,"unpinned":null,"visible":true,"closed":false,"archived":false,"bookmarked":null,"liked":null,"tags":[],"views":178,"like_count":0,"has_summary":false,"last_poster_username":"aqusvs","category_id":11,"pinned_globally":false,"featured_link":null,"has_accepted_answer":false,"posters":[{"extras":"latest single","description":"Original Poster, Most Recent Poster","user_id":43927,"primary_group_id":null}]},{"id":63013,"title":"Game doesn't feel smooth (Microstuttering)","fancy_title":"Game doesn&rsquo;t feel smooth (Microstuttering)","slug":"game-doesnt-feel-smooth-microstuttering","posts_count":1,"reply_count":0,"highest_post_number":1,"image_url":null,"created_at":"2020-03-16T07:45:31.022Z","last_posted_at":"2020-03-16T07:45:31.086Z","bumped":true,"bumped_at":"2020-08-12T02:23:03.542Z","archetype":"regular","unseen":false,"pinned":false,"unpinned":null,"visible":true,"closed":false,"archived":false,"bookmarked":null,"liked":null,"tags":[],"views":130,"like_count":0,"has_summary":false,"last_poster_username":"nordik","category_id":12,"pinned_globally":false,"featured_link":null,"has_accepted_answer":false,"posters":[{"extras":"latest single","description":"Original Poster, Most Recent Poster","user_id":43853,"primary_group_id":null}]},{"id":62524,"title":"I can't open up Black Mesa. Help me","fancy_title":"I can&rsquo;t open up Black Mesa. Help me","slug":"i-cant-open-up-black-mesa-help-me","posts_count":8,"reply_count":4,"highest_post_number":10,"image_url":null,"created_at":"2019-08-20T18:09:06.062Z","last_posted_at":"2020-08-11T20:38:42.323Z","bumped":true,"bumped_at":"2020-08-11T20:38:42.323Z","archetype":"regular","unseen":false,"pinned":false,"unpinned":null,"visible":true,"closed":false,"archived":false,"bookmarked":null,"liked":null,"tags":[],"views":2450,"like_count":0,"has_summary":false,"last_poster_username":"lucaswilde","category_id":12,"pinned_globally":false,"featured_link":null,"has_accepted_answer":false,"posters":[{"extras":null,"description":"Original Poster","user_id":43618,"primary_group_id":null},{"extras":null,"description":"Frequent Poster","user_id":299,"primary_group_id":null},{"extras":null,"description":"Frequent Poster","user_id":5060,"primary_group_id":null},{"extras":null,"description":"Frequent Poster","user_id":40754,"primary_group_id":null},{"extras":"latest","description":"Most Recent Poster","user_id":44022,"primary_group_id":null}]},{"id":63379,"title":"The game textures only load in a very low resolution","fancy_title":"The game textures only load in a very low resolution","slug":"the-game-textures-only-load-in-a-very-low-resolution","posts_count":2,"reply_count":0,"highest_post_number":2,"image_url":"https://leakfree.org/uploads/default/optimized/2X/6/6a254d130ec3fc4d2f7fbcd09c134ec79fad112a_2_1024x576.jpeg","created_at":"2020-08-03T10:00:10.144Z","last_posted_at":"2020-08-03T15:28:06.134Z","bumped":true,"bumped_at":"2020-08-03T15:28:06.134Z","archetype":"regular","unseen":false,"pinned":false,"unpinned":null,"visible":true,"closed":false,"archived":false,"bookmarked":null,"liked":null,"tags":[],"views":59,"like_count":0,"has_summary":false,"last_poster_username":"CPU","category_id":47,"pinned_globally":false,"featured_link":null,"has_accepted_answer":false,"posters":[{"extras":null,"description":"Original Poster","user_id":44029,"primary_group_id":null},{"extras":"latest","description":"Most Recent Poster","user_id":5060,"primary_group_id":null}]},{"id":63364,"title":"Rotating platform teleport puzzle: platforms aren't rotating","fancy_title":"Rotating platform teleport puzzle: platforms aren&rsquo;t rotating","slug":"rotating-platform-teleport-puzzle-platforms-arent-rotating","posts_count":2,"reply_count":0,"highest_post_number":2,"image_url":"https://leakfree.org/uploads/default/original/2X/d/dd9bd0e855b73f50ef06c992d313e523d56ce598.png","created_at":"2020-07-18T00:27:02.326Z","last_posted_at":"2020-07-18T16:26:41.844Z","bumped":true,"bumped_at":"2020-07-18T16:26:41.844Z","archetype":"regular","unseen":false,"pinned":false,"unpinned":null,"visible":true,"closed":false,"archived":false,"bookmarked":null,"liked":null,"tags":[],"views":83,"like_count":0,"has_summary":false,"last_poster_username":"CPU","category_id":47,"pinned_globally":false,"featured_link":null,"has_accepted_answer":false,"posters":[{"extras":null,"description":"Original Poster","user_id":44019,"primary_group_id":null},{"extras":"latest","description":"Most Recent Poster","user_id":5060,"primary_group_id":null}]},{"id":62899,"title":"pepperoni precipitation ","fancy_title":"pepperoni precipitation ","slug":"pepperoni-precipitation","posts_count":3,"reply_count":0,"highest_post_number":3,"image_url":null,"created_at":"2020-02-27T19:33:21.424Z","last_posted_at":"2020-07-06T00:15:16.637Z","bumped":true,"bumped_at":"2020-07-06T00:15:16.637Z","archetype":"regular","unseen":false,"pinned":false,"unpinned":null,"visible":true,"closed":false,"archived":false,"bookmarked":null,"liked":null,"tags":[],"views":1430,"like_count":0,"has_summary":false,"last_poster_username":"Medkit","category_id":12,"pinned_globally":false,"featured_link":null,"has_accepted_answer":false,"posters":[{"extras":null,"description":"Original Poster","user_id":43793,"primary_group_id":null},{"extras":null,"description":"Frequent Poster","user_id":43017,"primary_group_id":null},{"extras":"latest","description":"Most Recent Poster","user_id":6789,"primary_group_id":null}]},{"id":13794,"title":"How to report an issue","fancy_title":"How to report an issue","slug":"how-to-report-an-issue","posts_count":69,"reply_count":4,"highest_post_number":69,"image_url":null,"created_at":"2015-05-05T17:05:27.000Z","last_posted_at":"2020-06-29T14:31:42.426Z","bumped":true,"bumped_at":"2020-06-29T14:31:42.426Z","archetype":"regular","unseen":false,"pinned":true,"unpinned":null,"excerpt":"Crashes[/size] \nEvery time the game crashes, it will create an DMP (minidump) file in your \\Steam\\dumps folder. Your crash will be the newest entry in that folder named something similar to crash_bms.exe_20150505021705_1&hellip;","visible":true,"closed":false,"archived":false,"bookmarked":null,"liked":null,"tags":[],"views":24412,"like_count":1,"has_summary":true,"last_poster_username":"CPU","category_id":47,"pinned_globally":false,"featured_link":null,"has_accepted_answer":false,"posters":[{"extras":null,"description":"Original Poster","user_id":351,"primary_group_id":null},{"extras":null,"description":"Frequent Poster","user_id":39919,"primary_group_id":null},{"extras":null,"description":"Frequent Poster","user_id":518,"primary_group_id":null},{"extras":null,"description":"Frequent Poster","user_id":43003,"primary_group_id":null},{"extras":"latest","description":"Most Recent Poster","user_id":5060,"primary_group_id":null}]},{"id":62848,"title":"Is there any way to recover saves?","fancy_title":"Is there any way to recover saves?","slug":"is-there-any-way-to-recover-saves","posts_count":4,"reply_count":0,"highest_post_number":4,"image_url":null,"created_at":"2020-02-02T23:14:40.744Z","last_posted_at":"2020-02-02T23:52:32.925Z","bumped":true,"bumped_at":"2020-06-28T20:53:43.478Z","archetype":"regular","unseen":false,"pinned":false,"unpinned":null,"visible":true,"closed":false,"archived":false,"bookmarked":null,"liked":null,"tags":[],"views":499,"like_count":0,"has_summary":false,"last_poster_username":"Milloni","category_id":12,"pinned_globally":false,"featured_link":null,"has_accepted_answer":false,"posters":[{"extras":"latest","description":"Original Poster, Most Recent Poster","user_id":43721,"primary_group_id":null},{"extras":null,"description":"Frequent Poster","user_id":40529,"primary_group_id":null},{"extras":null,"description":"Frequent Poster","user_id":22194,"primary_group_id":null}]},{"id":63338,"title":"Can you make it so the flashlight doesn't come out of my dick?","fancy_title":"Can you make it so the flashlight doesn&rsquo;t come out of my dick?","slug":"can-you-make-it-so-the-flashlight-doesnt-come-out-of-my-dick","posts_count":2,"reply_count":0,"highest_post_number":2,"image_url":null,"created_at":"2020-06-28T09:10:25.147Z","last_posted_at":"2020-06-28T16:55:32.549Z","bumped":true,"bumped_at":"2020-06-28T16:55:32.549Z","archetype":"regular","unseen":false,"pinned":false,"unpinned":null,"visible":true,"closed":false,"archived":false,"bookmarked":null,"liked":null,"tags":[],"views":167,"like_count":0,"has_summary":false,"last_poster_username":"CPU","category_id":11,"pinned_globally":false,"featured_link":null,"has_accepted_answer":false,"posters":[{"extras":null,"description":"Original Poster","user_id":44006,"primary_group_id":null},{"extras":"latest","description":"Most Recent Poster","user_id":5060,"primary_group_id":null}]},{"id":63336,"title":"BM does not start on Ubuntu 20.04 - missing libs","fancy_title":"BM does not start on Ubuntu 20.04 - missing libs","slug":"bm-does-not-start-on-ubuntu-20-04-missing-libs","posts_count":2,"reply_count":0,"highest_post_number":2,"image_url":null,"created_at":"2020-06-28T01:17:35.628Z","last_posted_at":"2020-06-28T16:53:52.019Z","bumped":true,"bumped_at":"2020-06-28T16:53:52.019Z","archetype":"regular","unseen":false,"pinned":false,"unpinned":null,"visible":true,"closed":false,"archived":false,"bookmarked":null,"liked":null,"tags":[],"views":179,"like_count":0,"has_summary":false,"last_poster_username":"CPU","category_id":47,"pinned_globally":false,"featured_link":null,"has_accepted_answer":false,"posters":[{"extras":null,"description":"Original Poster","user_id":44005,"primary_group_id":null},{"extras":"latest","description":"Most Recent Poster","user_id":5060,"primary_group_id":null}]},{"id":63155,"title":"Game freezes when pressing ESC while quick-saving","fancy_title":"Game freezes when pressing ESC while quick-saving","slug":"game-freezes-when-pressing-esc-while-quick-saving","posts_count":3,"reply_count":0,"highest_post_number":3,"image_url":null,"created_at":"2020-04-10T12:49:31.798Z","last_posted_at":"2020-06-27T04:37:35.833Z","bumped":true,"bumped_at":"2020-06-27T04:37:35.833Z","archetype":"regular","unseen":false,"pinned":false,"unpinned":null,"visible":true,"closed":false,"archived":false,"bookmarked":null,"liked":null,"tags":[],"views":237,"like_count":0,"has_summary":false,"last_poster_username":"CPU","category_id":47,"pinned_globally":false,"featured_link":null,"has_accepted_answer":false,"posters":[{"extras":null,"description":"Original Poster","user_id":43921,"primary_group_id":null},{"extras":null,"description":"Frequent Poster","user_id":44003,"primary_group_id":null},{"extras":"latest","description":"Most Recent Poster","user_id":5060,"primary_group_id":null}]},{"id":63327,"title":"ED_Alloc: no free edicts ... Catastrophic Game Crashing Continues","fancy_title":"ED_Alloc: no free edicts &hellip; Catastrophic Game Crashing Continues","slug":"ed-alloc-no-free-edicts-catastrophic-game-crashing-continues","posts_count":1,"reply_count":0,"highest_post_number":1,"image_url":null,"created_at":"2020-06-24T00:18:48.453Z","last_posted_at":"2020-06-24T00:18:48.534Z","bumped":true,"bumped_at":"2020-06-24T00:18:48.534Z","archetype":"regular","unseen":false,"pinned":false,"unpinned":null,"visible":true,"closed":false,"archived":false,"bookmarked":null,"liked":null,"tags":[],"views":236,"like_count":0,"has_summary":false,"last_poster_username":"Catsmack","category_id":47,"pinned_globally":false,"featured_link":null,"has_accepted_answer":false,"posters":[{"extras":"latest single","description":"Original Poster, Most Recent Poster","user_id":43946,"primary_group_id":null}]},{"id":62775,"title":"ED_Alloc: no free edicts","fancy_title":"ED_Alloc: no free edicts","slug":"ed-alloc-no-free-edicts","posts_count":14,"reply_count":2,"highest_post_number":15,"image_url":null,"created_at":"2020-01-04T22:45:09.797Z","last_posted_at":"2020-06-23T23:25:15.107Z","bumped":true,"bumped_at":"2020-06-23T23:37:05.075Z","archetype":"regular","unseen":false,"pinned":false,"unpinned":null,"visible":true,"closed":false,"archived":false,"bookmarked":null,"liked":null,"tags":[],"views":5542,"like_count":5,"has_summary":false,"last_poster_username":"Catsmack","category_id":12,"pinned_globally":false,"featured_link":null,"has_accepted_answer":false,"posters":[{"extras":null,"description":"Original Poster","user_id":43733,"primary_group_id":null},{"extras":null,"description":"Frequent Poster","user_id":22194,"primary_group_id":null},{"extras":null,"description":"Frequent Poster","user_id":43805,"primary_group_id":null},{"extras":null,"description":"Frequent Poster","user_id":43955,"primary_group_id":null},{"extras":"latest","description":"Most Recent Poster","user_id":43946,"primary_group_id":null}]},{"id":63145,"title":"Dark screen when playing Black mesa","fancy_title":"Dark screen when playing Black mesa","slug":"dark-screen-when-playing-black-mesa","posts_count":3,"reply_count":0,"highest_post_number":3,"image_url":null,"created_at":"2020-04-07T20:44:50.955Z","last_posted_at":"2020-06-23T01:41:38.974Z","bumped":true,"bumped_at":"2020-06-23T01:41:38.974Z","archetype":"regular","unseen":false,"pinned":false,"unpinned":null,"visible":true,"closed":false,"archived":false,"bookmarked":null,"liked":null,"tags":[],"views":173,"like_count":0,"has_summary":false,"last_poster_username":"CPU","category_id":12,"pinned_globally":false,"featured_link":null,"has_accepted_answer":false,"posters":[{"extras":null,"description":"Original Poster","user_id":43916,"primary_group_id":null},{"extras":null,"description":"Frequent Poster","user_id":44001,"primary_group_id":null},{"extras":"latest","description":"Most Recent Poster","user_id":5060,"primary_group_id":null}]},{"id":63325,"title":"Dark Areas/Overdark glitch","fancy_title":"Dark Areas/Overdark glitch","slug":"dark-areas-overdark-glitch","posts_count":1,"reply_count":0,"highest_post_number":1,"image_url":null,"created_at":"2020-06-22T20:32:38.166Z","last_posted_at":"2020-06-22T20:32:38.236Z","bumped":true,"bumped_at":"2020-06-22T20:32:38.236Z","archetype":"regular","unseen":false,"pinned":false,"unpinned":null,"visible":true,"closed":false,"archived":false,"bookmarked":null,"liked":null,"tags":[],"views":250,"like_count":0,"has_summary":false,"last_poster_username":"NigelHellhound","category_id":12,"pinned_globally":false,"featured_link":null,"has_accepted_answer":false,"posters":[{"extras":"latest single","description":"Original Poster, Most Recent Poster","user_id":44001,"primary_group_id":null}]},{"id":63323,"title":"Black mesa We-ve got hostile pre disaster","fancy_title":"Black mesa We-ve got hostile pre disaster","slug":"black-mesa-we-ve-got-hostile-pre-disaster","posts_count":1,"reply_count":0,"highest_post_number":1,"image_url":null,"created_at":"2020-06-21T12:35:01.833Z","last_posted_at":"2020-06-21T12:35:01.966Z","bumped":true,"bumped_at":"2020-06-21T12:35:01.966Z","archetype":"regular","unseen":false,"pinned":false,"unpinned":null,"visible":true,"closed":false,"archived":false,"bookmarked":null,"liked":null,"tags":[],"views":133,"like_count":0,"has_summary":false,"last_poster_username":"sam.devray","category_id":47,"pinned_globally":false,"featured_link":null,"has_accepted_answer":false,"posters":[{"extras":"latest single","description":"Original Poster, Most Recent Poster","user_id":43991,"primary_group_id":null}]},{"id":63319,"title":"Game crashes while loading recent saved games","fancy_title":"Game crashes while loading recent saved games","slug":"game-crashes-while-loading-recent-saved-games","posts_count":3,"reply_count":0,"highest_post_number":3,"image_url":null,"created_at":"2020-06-17T22:23:06.794Z","last_posted_at":"2020-06-20T16:09:59.141Z","bumped":true,"bumped_at":"2020-06-20T16:09:59.141Z","archetype":"regular","unseen":false,"pinned":false,"unpinned":null,"visible":true,"closed":false,"archived":false,"bookmarked":null,"liked":null,"tags":[],"views":133,"like_count":0,"has_summary":false,"last_poster_username":"CPU","category_id":47,"pinned_globally":false,"featured_link":null,"has_accepted_answer":false,"posters":[{"extras":null,"description":"Original Poster","user_id":44000,"primary_group_id":null},{"extras":"latest","description":"Most Recent Poster","user_id":5060,"primary_group_id":null}]},{"id":63238,"title":"Problems with the Male Scientist models","fancy_title":"Problems with the Male Scientist models","slug":"problems-with-the-male-scientist-models","posts_count":12,"reply_count":5,"highest_post_number":12,"image_url":"https://leakfree.org/uploads/default/original/2X/6/6f1226b6acccb7a22adb9e45899c484c2afadaf0.png","created_at":"2020-05-10T16:02:19.123Z","last_posted_at":"2020-06-17T19:16:38.004Z","bumped":true,"bumped_at":"2020-06-17T19:16:38.004Z","archetype":"regular","unseen":false,"pinned":false,"unpinned":null,"visible":true,"closed":false,"archived":false,"bookmarked":null,"liked":null,"tags":["windows"],"views":314,"like_count":0,"has_summary":false,"last_poster_username":"LimeSquidBlackMesa","category_id":47,"pinned_globally":false,"featured_link":null,"has_accepted_answer":false,"posters":[{"extras":"latest","description":"Original Poster, Most Recent Poster","user_id":43963,"primary_group_id":null},{"extras":null,"description":"Frequent Poster","user_id":40529,"primary_group_id":null},{"extras":null,"description":"Frequent Poster","user_id":39769,"primary_group_id":null},{"extras":null,"description":"Frequent Poster","user_id":5060,"primary_group_id":null}]},{"id":63117,"title":"Thanks for the best game experience I've had in 20 years","fancy_title":"Thanks for the best game experience I&rsquo;ve had in 20 years","slug":"thanks-for-the-best-game-experience-ive-had-in-20-years","posts_count":2,"reply_count":0,"highest_post_number":2,"image_url":null,"created_at":"2020-04-04T16:29:54.993Z","last_posted_at":"2020-04-04T16:32:44.920Z","bumped":true,"bumped_at":"2020-06-17T02:04:41.399Z","archetype":"regular","unseen":false,"pinned":false,"unpinned":null,"visible":true,"closed":false,"archived":false,"bookmarked":null,"liked":null,"tags":[],"views":198,"like_count":3,"has_summary":false,"last_poster_username":"CatzEyes93","category_id":11,"pinned_globally":false,"featured_link":null,"has_accepted_answer":false,"posters":[{"extras":null,"description":"Original Poster","user_id":43901,"primary_group_id":null},{"extras":"latest","description":"Most Recent Poster","user_id":299,"primary_group_id":null}]},{"id":10491,"title":"SURFACE TENSION - Stuck here?","fancy_title":"SURFACE TENSION - Stuck here?","slug":"surface-tension-stuck-here","posts_count":134,"reply_count":2,"highest_post_number":134,"image_url":null,"created_at":"2012-09-17T05:15:37.000Z","last_posted_at":"2020-06-15T14:07:08.267Z","bumped":true,"bumped_at":"2020-06-15T14:07:08.267Z","archetype":"regular","unseen":false,"pinned":true,"unpinned":null,"excerpt":"Ask here for tips and tricks about this chapter. Tell where you’re stuck and others will give the solutions. \n(Please keep always on topic. Don’t post about other chapters or create random chit-chat here)","visible":true,"closed":false,"archived":false,"bookmarked":null,"liked":null,"tags":[],"views":99691,"like_count":0,"has_summary":false,"last_poster_username":"Andyv","category_id":12,"pinned_globally":false,"featured_link":null,"has_accepted_answer":false,"posters":[{"extras":null,"description":"Original Poster","user_id":2643,"primary_group_id":null},{"extras":null,"description":"Frequent Poster","user_id":18192,"primary_group_id":null},{"extras":null,"description":"Frequent Poster","user_id":1014,"primary_group_id":null},{"extras":null,"description":"Frequent Poster","user_id":14297,"primary_group_id":null},{"extras":"latest","description":"Most Recent Poster","user_id":43999,"primary_group_id":null}]},{"id":63310,"title":"German voice localisation","fancy_title":"German voice localisation","slug":"german-voice-localisation","posts_count":2,"reply_count":0,"highest_post_number":2,"image_url":null,"created_at":"2020-06-10T18:19:22.103Z","last_posted_at":"2020-06-10T22:33:25.208Z","bumped":true,"bumped_at":"2020-06-10T22:33:25.208Z","archetype":"regular","unseen":false,"pinned":false,"unpinned":null,"visible":true,"closed":false,"archived":false,"bookmarked":null,"liked":null,"tags":[],"views":108,"like_count":0,"has_summary":false,"last_poster_username":"CPU","category_id":6,"pinned_globally":false,"featured_link":null,"has_accepted_answer":false,"posters":[{"extras":null,"description":"Original Poster","user_id":43995,"primary_group_id":null},{"extras":"latest","description":"Most Recent Poster","user_id":5060,"primary_group_id":null}]},{"id":62337,"title":"Vortiguants still look like garbage :(","fancy_title":"Vortiguants still look like garbage :frowning:","slug":"vortiguants-still-look-like-garbage","posts_count":34,"reply_count":20,"highest_post_number":34,"image_url":"https://leakfree.org/uploads/default/optimized/2X/e/ea0584a57d3abdd701afcf1a5bdcccfcd3d0f30d_2_1024x397.jpeg","created_at":"2019-06-22T06:39:15.188Z","last_posted_at":"2020-06-09T08:44:49.971Z","bumped":true,"bumped_at":"2020-06-09T08:44:49.971Z","archetype":"regular","unseen":false,"pinned":false,"unpinned":null,"visible":true,"closed":false,"archived":false,"bookmarked":null,"liked":null,"tags":[],"views":4587,"like_count":34,"has_summary":false,"last_poster_username":"Crawfish","category_id":11,"pinned_globally":false,"featured_link":null,"has_accepted_answer":false,"posters":[{"extras":null,"description":"Original Poster","user_id":4458,"primary_group_id":null},{"extras":null,"description":"Frequent Poster","user_id":40409,"primary_group_id":null},{"extras":null,"description":"Frequent Poster","user_id":43327,"primary_group_id":null},{"extras":null,"description":"Frequent Poster","user_id":1068,"primary_group_id":null},{"extras":"latest","description":"Most Recent Poster","user_id":39769,"primary_group_id":null}]},{"id":63303,"title":"Surround Sound under Linux","fancy_title":"Surround Sound under Linux","slug":"surround-sound-under-linux","posts_count":1,"reply_count":0,"highest_post_number":1,"image_url":null,"created_at":"2020-06-06T20:30:03.297Z","last_posted_at":"2020-06-06T20:30:03.440Z","bumped":true,"bumped_at":"2020-06-06T20:30:03.440Z","archetype":"regular","unseen":false,"pinned":false,"unpinned":null,"visible":true,"closed":false,"archived":false,"bookmarked":null,"liked":null,"tags":[],"views":85,"like_count":0,"has_summary":false,"last_poster_username":"hompen","category_id":12,"pinned_globally":false,"featured_link":null,"has_accepted_answer":false,"posters":[{"extras":"latest single","description":"Original Poster, Most Recent Poster","user_id":43992,"primary_group_id":null}]},{"id":63297,"title":"Black mesa mod - steam workshop publishing tool error","fancy_title":"Black mesa mod - steam workshop publishing tool error","slug":"black-mesa-mod-steam-workshop-publishing-tool-error","posts_count":1,"reply_count":0,"highest_post_number":1,"image_url":"https://leakfree.org/uploads/default/optimized/2X/3/364a99a696ebc5096d58ce4f18d20075bd812ef3_2_1024x637.jpeg","created_at":"2020-05-29T13:11:25.805Z","last_posted_at":"2020-05-29T13:11:25.895Z","bumped":true,"bumped_at":"2020-05-29T13:11:25.895Z","archetype":"regular","unseen":false,"pinned":false,"unpinned":null,"visible":true,"closed":false,"archived":false,"bookmarked":null,"liked":null,"tags":[],"views":130,"like_count":0,"has_summary":false,"last_poster_username":"Vasi","category_id":11,"pinned_globally":false,"featured_link":null,"has_accepted_answer":false,"posters":[{"extras":"latest single","description":"Original Poster, Most Recent Poster","user_id":43978,"primary_group_id":null}]},{"id":62940,"title":"Unable to bind keys","fancy_title":"Unable to bind keys","slug":"unable-to-bind-keys","posts_count":6,"reply_count":3,"highest_post_number":6,"image_url":null,"created_at":"2020-03-07T22:10:49.031Z","last_posted_at":"2020-04-07T01:08:05.871Z","bumped":true,"bumped_at":"2020-05-29T02:00:31.120Z","archetype":"regular","unseen":false,"pinned":false,"unpinned":null,"visible":true,"closed":false,"archived":false,"bookmarked":null,"liked":null,"tags":[],"views":766,"like_count":2,"has_summary":false,"last_poster_username":"andrewxc","category_id":12,"pinned_globally":false,"featured_link":null,"has_accepted_answer":false,"posters":[{"extras":null,"description":"Original Poster","user_id":43817,"primary_group_id":null},{"extras":null,"description":"Frequent Poster","user_id":22194,"primary_group_id":null},{"extras":null,"description":"Frequent Poster","user_id":43881,"primary_group_id":null},{"extras":null,"description":"Frequent Poster","user_id":43911,"primary_group_id":null},{"extras":"latest","description":"Most Recent Poster","user_id":19806,"primary_group_id":null}]},{"id":63067,"title":"Cannot Carry Pizza Through Door (Surface Tension, bm_c2a5h)","fancy_title":"Cannot Carry Pizza Through Door (Surface Tension, bm_c2a5h)","slug":"cannot-carry-pizza-through-door-surface-tension-bm-c2a5h","posts_count":5,"reply_count":1,"highest_post_number":5,"image_url":"https://leakfree.org/uploads/default/optimized/2X/e/e34fd2235cf279a6d98e240c404f926058787ccf_2_1024x576.jpeg","created_at":"2020-03-25T19:43:43.783Z","last_posted_at":"2020-05-28T13:00:05.920Z","bumped":true,"bumped_at":"2020-05-28T13:00:05.920Z","archetype":"regular","unseen":false,"pinned":false,"unpinned":null,"visible":true,"closed":false,"archived":false,"bookmarked":null,"liked":null,"tags":[],"views":342,"like_count":1,"has_summary":false,"last_poster_username":"RaverDave2k","category_id":47,"pinned_globally":false,"featured_link":null,"has_accepted_answer":false,"posters":[{"extras":null,"description":"Original Poster","user_id":43879,"primary_group_id":null},{"extras":null,"description":"Frequent Poster","user_id":43895,"primary_group_id":null},{"extras":"latest","description":"Most Recent Poster","user_id":43985,"primary_group_id":null}]},{"id":63279,"title":"A way to change the HUD color","fancy_title":"A way to change the HUD color","slug":"a-way-to-change-the-hud-color","posts_count":1,"reply_count":0,"highest_post_number":1,"image_url":null,"created_at":"2020-05-24T18:56:33.489Z","last_posted_at":"2020-05-24T18:56:33.557Z","bumped":true,"bumped_at":"2020-05-24T18:56:33.557Z","archetype":"regular","unseen":false,"pinned":false,"unpinned":null,"visible":true,"closed":false,"archived":false,"bookmarked":null,"liked":null,"tags":[],"views":81,"like_count":0,"has_summary":false,"last_poster_username":"Lilchubby","category_id":12,"pinned_globally":false,"featured_link":null,"has_accepted_answer":false,"posters":[{"extras":"latest single","description":"Original Poster, Most Recent Poster","user_id":43979,"primary_group_id":null}]},{"id":63190,"title":"What does this DALsys machine in Questionable Ethics do?","fancy_title":"What does this DALsys machine in Questionable Ethics do?","slug":"what-does-this-dalsys-machine-in-questionable-ethics-do","posts_count":2,"reply_count":0,"highest_post_number":2,"image_url":"https://leakfree.org/uploads/default/original/2X/5/56c86137c9aa88cd1c2b93757f4ea159a4861873.png","created_at":"2020-04-17T14:55:48.043Z","last_posted_at":"2020-05-06T14:43:16.318Z","bumped":true,"bumped_at":"2020-05-23T02:54:52.063Z","archetype":"regular","unseen":false,"pinned":false,"unpinned":null,"visible":true,"closed":false,"archived":false,"bookmarked":null,"liked":null,"tags":[],"views":252,"like_count":0,"has_summary":false,"last_poster_username":"Viewer","category_id":6,"pinned_globally":false,"featured_link":null,"has_accepted_answer":false,"posters":[{"extras":null,"description":"Original Poster","user_id":43940,"primary_group_id":null},{"extras":"latest","description":"Most Recent Poster","user_id":990,"primary_group_id":null}]},{"id":63273,"title":"Game crash at Interloper green tube","fancy_title":"Game crash at Interloper green tube","slug":"game-crash-at-interloper-green-tube","posts_count":1,"reply_count":0,"highest_post_number":1,"image_url":null,"created_at":"2020-05-22T00:12:58.277Z","last_posted_at":"2020-05-22T00:12:58.358Z","bumped":true,"bumped_at":"2020-05-22T00:12:58.358Z","archetype":"regular","unseen":false,"pinned":false,"unpinned":null,"visible":true,"closed":false,"archived":false,"bookmarked":null,"liked":null,"tags":[],"views":172,"like_count":0,"has_summary":false,"last_poster_username":"Giodude","category_id":47,"pinned_globally":false,"featured_link":null,"has_accepted_answer":false,"posters":[{"extras":"latest single","description":"Original Poster, Most Recent Poster","user_id":43975,"primary_group_id":null}]},{"id":63267,"title":"Massive Bug/Glitch Report","fancy_title":"Massive Bug/Glitch Report","slug":"massive-bug-glitch-report","posts_count":1,"reply_count":0,"highest_post_number":1,"image_url":null,"created_at":"2020-05-18T21:17:38.559Z","last_posted_at":"2020-05-18T21:17:38.680Z","bumped":true,"bumped_at":"2020-05-18T21:17:38.680Z","archetype":"regular","unseen":false,"pinned":false,"unpinned":null,"visible":true,"closed":false,"archived":false,"bookmarked":null,"liked":null,"tags":[],"views":466,"like_count":0,"has_summary":false,"last_poster_username":"neon5916","category_id":47,"pinned_globally":false,"featured_link":null,"has_accepted_answer":false,"posters":[{"extras":"latest single","description":"Original Poster, Most Recent Poster","user_id":43971,"primary_group_id":null}]}]}}